<mvc:View controllerName="ui5.sales.controller.List" xmlns="sap.m" xmlns:mvc="sap.ui.core.mvc" xmlns:l="sap.ui.layout" xmlns:f="sap.f" displayBlock="true">
	<f:DynamicPage id="listDynamicPage">
		<f:title><f:DynamicPageTitle><f:heading><Title text="{i18n>pageTitle}" /></f:heading></f:DynamicPageTitle></f:title>
		<f:header><f:DynamicPageHeader pinnable="true">
			<l:Grid defaultSpan="XL3 L3 M6 S12" hSpacing="1" vSpacing="1">
							<VBox class="sapUiSmallMargin"><Title text="{ui>/kpi/open}" level="H2" /><Text text="{i18n>openLabel}" /></VBox>
							<VBox class="sapUiSmallMargin"><Title text="{ui>/kpi/inProcess}" level="H2" /><Text text="{i18n>inProcessLabel}" /></VBox>
							<VBox class="sapUiSmallMargin"><Title text="{ui>/kpi/completed}" level="H2" /><Text text="{i18n>completedLabel}" /></VBox>
							<VBox class="sapUiSmallMargin"><Title text="{ui>/kpi/revenue}" level="H2" /><Text text="{i18n>revenueLabel}" /></VBox>
			</l:Grid>
			<SearchField search=".onSearch" placeholder="{i18n>searchPlaceholder}" width="20rem" />
		</f:DynamicPageHeader></f:header>
		<f:content>
			<List id="ordersList" headerText="{i18n>ordersListTitle}" items="{ path: '/SalesOrders', parameters: { $count: true, $orderby: 'orderDate desc', $select: 'orderId,customer,status,amount,currency,priority' } }">
				<ObjectListItem title="{customer}" number="{ parts: ['amount', 'currency'], type: 'sap.ui.model.type.Currency', formatOptions: { showMeasure: false } }" numberUnit="{currency}" type="Active" press=".onOrderPress" highlight="{= ${priority} === 'High' ? 'Error' : 'None' }">
					<firstStatus><ObjectStatus text="{status}" state="{ path: 'status', formatter: '.formatter.statusState' }" /></firstStatus>
					<attributes><ObjectAttribute text="{orderId}" /></attributes>
				</ObjectListItem>
			</List>
		</f:content>
		<f:footer><OverflowToolbar><ToolbarSpacer /><Button text="{i18n>createButton}" type="Emphasized" press=".onCreate" /></OverflowToolbar></f:footer>
	</f:DynamicPage>
</mvc:View>
